Metadata-Version: 2.1
Name: dFBApy
Version: 0.0.4
Summary: Simulate dynamic Flux Balance Analysis (dFBA) of BiGG models, with compatibility to the BiGG-SABIO module.
Home-page: https://github.com/freiburgermsu/dfbapy
Author: Andrew Freiburger
Author-email: andrewfreiburger@gmail.com
License: MIT
Keywords: chemistry,biology,metabolism,metabolome,flux,balance,analysis,biochemistry,FBA,dynamic
Platform: UNKNOWN
License-File: LICENSE
